evernote2md/__init__.py
evernote2md/__main__.py
evernote2md-1.0.0.dist-info/METADATA
evernote2md-1.0.0.dist-info/WHEEL
evernote2md-1.0.0.dist-info/entry_points.txt
evernote2md-1.0.0.dist-info/licenses/LICENSE
evernote2md-1.0.0.dist-info/RECORD
