Metadata-Version: 2.3
Name: evernote2md
Version: 1.0.0
Summary: A command line tool to make a Markdown vault from an Evernote export
Project-URL: Homepage, https://github.com/davep/evernote2md
Project-URL: Repository, https://github.com/davep/evernote2md
Project-URL: Documentation, https://github.com/davep/evernote2md
Project-URL: Issues, https://github.com/davep/evernote2md/issues
Author-email: Dave Pearson <davep@davep.org>
License:                     GNU GENERAL PUBLIC LICENSE
License-File: LICENSE
Requires-Python: >=3.12
Requires-Dist: markdownify>=0.13.1
Requires-Dist: pytz>=2024.2
